BottleSaml/SamlSP.py
BottleSaml/__init__.py
BottleSaml/reqID.py
BottleSaml-22.8.27.dist-info/License.txt
BottleSaml-22.8.27.dist-info/METADATA
BottleSaml-22.8.27.dist-info/WHEEL
BottleSaml-22.8.27.dist-info/top_level.txt
BottleSaml-22.8.27.dist-info/RECORD
