Metadata-Version: 2.1
Name: BottleSaml
Version: 22.8.27
Summary: SAML Service Provider for Bottle
Home-page: https://github.com/Glocktober/BottleSaml
Author: gunville
Author-email: rk13088@yahoo.com
Project-URL: repo, https://github.com/Glocktober/BottleSaml
Project-URL: overview, https://github.com/Glocktober/BottleSaml/blob/main/README.md
Keywords: 'bottle saml plugin'
Classifier: Programming Language :: Python :: 3
Classifier: License :: OSI Approved :: MIT License
Classifier: Operating System :: OS Independent
Classifier: Framework :: Bottle
Requires-Python: >=3.8
License-File: License.txt
Requires-Dist: bottle (>=0.12.0)
Requires-Dist: BottleSessions (>=21.07.01)
Requires-Dist: BottleAuth (>=21.09.01)
Requires-Dist: minisaml (==22.4)
